{"changelog.md":"cb7af977","code_of_conduct.md":"064d9c12","contributing.md":"091eca23","internals.ts.md":"1e57b7c4","maintainers.md":"37a7d77b","readme.md":"b5494ca2","roadmap.ts.md":"66b0034f","spec.ts.md":"9158626d","testing.ts.md":"37f011c2","crates_fadroma-platform-scrt_readme.md":"91811254","crates_fadroma-proc-derive_readme.md":"3e0f52da","crates_fadroma_readme.md":"65bf4f23","crates_fadroma_composability_readme.md":"c6a02d8d","crates_fadroma_ensemble_readme.md":"499ed4df","crates_fadroma_math_readme.md":"96efd6cc","crates_fadroma_snip20_impl_readme.md":"b51acc78","crates_fadroma_snip20_impl_tests_example-receiver_readme.md":"4610817b","crates_fadroma_storage_readme.md":"b21a02a1","examples_readme.md":"9b5f3e69","examples_echo_readme.md":"3f202b51","fixtures_readme.md":"7d8dbcd8","fixtures_genesis_readme.md":"41afe66b","guide_readme.md":"e59a285e","guide_client.md":"0033a04d","guide_contributing.md":"de35f771","guide_derive.md":"a8eb1cbc","guide_ensemble.md":"144811d4","guide_mocknet.md":"e671537e","guide_operating.md":"f6c9f670","guide_ops.md":"1bf27206","guide_overview.md":"3c49561a","guide_prelude.md":"defc9684","guide_project-setup.md":"45afaa9d","index.md":"8f385eba","packages_client-cw-0.16_readme.md":"a7633c7c","packages_client-cw-1_readme.md":"77d53945","packages_client-evm_readme.md":"a715b3ff","packages_client-scrt-amino_readme.md":"d48fa70b","packages_client-scrt-grpc_readme.md":"5a53c3b3","packages_client-scrt_readme.md":"f633d226","packages_client_readme.md":"e64c1650","packages_ops-scrt_readme.md":"a2371115","packages_ops_readme.md":"39104752","packages_tokens_readme.md":"0c19852a"}
